creditcard_identifier/__init__.py
creditcard_identifier/brands.py
creditcard_identifier/brands_detailed.py
creditcard_identifier/cards-detailed.json
creditcard_identifier/validator.py
creditcard_identifier-2.3.0.dist-info/licenses/LICENSE
creditcard_identifier-2.3.0.dist-info/METADATA
creditcard_identifier-2.3.0.dist-info/WHEEL
creditcard_identifier-2.3.0.dist-info/top_level.txt
creditcard_identifier-2.3.0.dist-info/RECORD
