Metadata-Version: 2.4
Name: creditcard-identifier
Version: 2.3.0
Summary: Credit card BIN validation using bin-cc data
Author: Renato Viço
License: MIT
Project-URL: Homepage, https://github.com/renatovico/bin-cc
Project-URL: Repository, https://github.com/renatovico/bin-cc
Project-URL: Documentation, https://github.com/renatovico/bin-cc/tree/master/libs/python
Keywords: credit-card,validation,bin,card-brand
Classifier: Development Status :: 4 - Beta
Classifier: Intended Audience :: Developers
Classifier: License :: OSI Approved :: MIT License
Classifier: Programming Language :: Python :: 3
Classifier: Programming Language :: Python :: 3.6
Classifier: Programming Language :: Python :: 3.7
Classifier: Programming Language :: Python :: 3.8
Classifier: Programming Language :: Python :: 3.9
Classifier: Programming Language :: Python :: 3.10
Classifier: Programming Language :: Python :: 3.11
Classifier: Programming Language :: Python :: 3.12
Requires-Python: >=3.6
License-File: LICENSE
Dynamic: license-file
